sphinxcontrib_matlabdomain-0.22.1-py3.11-nspkg.pth
sphinxcontrib/mat_directives.py
sphinxcontrib/mat_documenters.py
sphinxcontrib/mat_lexer.py
sphinxcontrib/mat_parser.py
sphinxcontrib/mat_types.py
sphinxcontrib/matlab.py
sphinxcontrib_matlabdomain-0.22.1.dist-info/AUTHORS
sphinxcontrib_matlabdomain-0.22.1.dist-info/LICENSE
sphinxcontrib_matlabdomain-0.22.1.dist-info/METADATA
sphinxcontrib_matlabdomain-0.22.1.dist-info/WHEEL
sphinxcontrib_matlabdomain-0.22.1.dist-info/namespace_packages.txt
sphinxcontrib_matlabdomain-0.22.1.dist-info/top_level.txt
sphinxcontrib_matlabdomain-0.22.1.dist-info/RECORD
