Metadata-Version: 2.1
Name: sphinxcontrib-matlabdomain
Version: 0.22.1
Summary: Sphinx "matlabdomain" extension
Home-page: https://github.com/sphinx-contrib/matlabdomain
Download-URL: http://pypi.python.org/pypi/sphinxcontrib-matlabdomain
Author: Jørgen Cederberg
Author-email: jorgen@cederberg.be
License: BSD
Platform: any
Classifier: Development Status :: 4 - Beta
Classifier: Environment :: Console
Classifier: Environment :: Web Environment
Classifier: Intended Audience :: Developers
Classifier: License :: OSI Approved :: BSD License
Classifier: Operating System :: OS Independent
Classifier: Programming Language :: Python
Classifier: Topic :: Documentation
Classifier: Topic :: Utilities
Classifier: Framework :: Sphinx :: Extension
Classifier: Framework :: Sphinx :: Domain
License-File: LICENSE
License-File: AUTHORS
Requires-Dist: Sphinx>=4.0.0
Requires-Dist: Pygments>=2.0.1
